{
  "$schema": "https://raw.githubusercontent.com/asledgehammer/PZ-Rosetta-Schema/main/rosetta-schema.json",
  "namespaces": {
    "zombie-characters-professions": {
      "Profession": {
        "constructors": [
          {
            "modifiers": [
              "public"
            ],
            "parameters": [
              {
                "name": "type",
                "type": {
                  "nullable": true,
                  "basic": "String"
                }
              },
              {
                "name": "name",
                "type": {
                  "nullable": true,
                  "basic": "String"
                }
              },
              {
                "name": "IconPathname",
                "type": {
                  "nullable": true,
                  "basic": "String"
                }
              },
              {
                "name": "cost",
                "type": {
                  "nullable": false,
                  "basic": "int"
                }
              },
              {
                "name": "desc",
                "type": {
                  "nullable": true,
                  "basic": "String"
                }
              }
            ]
          }
        ],
        "extends": "Object",
        "methods": [
          {
            "name": "addFreeTrait",
            "returns": {
              "type": {
                "nullable": false,
                "basic": "void"
              }
            },
            "modifiers": [
              "public"
            ],
            "parameters": [
              {
                "name": "trait",
                "type": {
                  "nullable": true,
                  "basic": "String"
                }
              }
            ]
          },
          {
            "name": "addXPBoost",
            "returns": {
              "type": {
                "nullable": false,
                "basic": "void"
              }
            },
            "modifiers": [
              "public"
            ],
            "parameters": [
              {
                "name": "perk",
                "type": {
                  "nullable": true,
                  "basic": "Perk"
                }
              },
              {
                "name": "level",
                "type": {
                  "nullable": false,
                  "basic": "int"
                }
              }
            ]
          },
          {
            "name": "getCost",
            "returns": {
              "notes": "the cost",
              "type": {
                "nullable": false,
                "basic": "int"
              }
            },
            "modifiers": [
              "public"
            ]
          },
          {
            "name": "getDescription",
            "returns": {
              "notes": "the description",
              "type": {
                "nullable": true,
                "basic": "String"
              }
            },
            "modifiers": [
              "public"
            ]
          },
          {
            "name": "getFreeRecipes",
            "returns": {
              "type": {
                "nullable": true,
                "basic": "List"
              }
            },
            "modifiers": [
              "public"
            ]
          },
          {
            "name": "getFreeTraitStack",
            "returns": {
              "notes": "the FreeTraitStack",
              "type": {
                "nullable": true,
                "basic": "Stack"
              }
            },
            "modifiers": [
              "public"
            ]
          },
          {
            "name": "getFreeTraits",
            "returns": {
              "type": {
                "nullable": true,
                "basic": "ArrayList"
              }
            },
            "modifiers": [
              "public"
            ]
          },
          {
            "name": "getIconPath",
            "returns": {
              "type": {
                "nullable": true,
                "basic": "String"
              }
            },
            "modifiers": [
              "public"
            ]
          },
          {
            "name": "getLabel",
            "returns": {
              "type": {
                "nullable": true,
                "basic": "String"
              }
            },
            "modifiers": [
              "public"
            ]
          },
          {
            "name": "getLeftLabel",
            "returns": {
              "type": {
                "nullable": true,
                "basic": "String"
              }
            },
            "modifiers": [
              "public"
            ]
          },
          {
            "name": "getName",
            "returns": {
              "notes": "the name",
              "type": {
                "nullable": true,
                "basic": "String"
              }
            },
            "modifiers": [
              "public"
            ]
          },
          {
            "name": "getRightLabel",
            "returns": {
              "type": {
                "nullable": true,
                "basic": "String"
              }
            },
            "modifiers": [
              "public"
            ]
          },
          {
            "name": "getTexture",
            "returns": {
              "type": {
                "nullable": true,
                "basic": "Texture"
              }
            },
            "modifiers": [
              "public"
            ]
          },
          {
            "name": "getType",
            "returns": {
              "notes": "the type",
              "type": {
                "nullable": true,
                "basic": "String"
              }
            },
            "modifiers": [
              "public"
            ]
          },
          {
            "name": "getXPBoostMap",
            "returns": {
              "type": {
                "nullable": true,
                "basic": "HashMap"
              }
            },
            "modifiers": [
              "public"
            ]
          },
          {
            "name": "setCost",
            "returns": {
              "type": {
                "nullable": false,
                "basic": "void"
              }
            },
            "modifiers": [
              "public"
            ],
            "parameters": [
              {
                "notes": "the cost to set",
                "name": "cost",
                "type": {
                  "nullable": false,
                  "basic": "int"
                }
              }
            ]
          },
          {
            "name": "setDescription",
            "returns": {
              "type": {
                "nullable": false,
                "basic": "void"
              }
            },
            "modifiers": [
              "public"
            ],
            "parameters": [
              {
                "notes": "the description to set",
                "name": "description",
                "type": {
                  "nullable": true,
                  "basic": "String"
                }
              }
            ]
          },
          {
            "name": "setFreeRecipes",
            "returns": {
              "type": {
                "nullable": false,
                "basic": "void"
              }
            },
            "modifiers": [
              "public"
            ],
            "parameters": [
              {
                "name": "freeRecipes",
                "type": {
                  "nullable": true,
                  "basic": "List",
                  "full": "List\u003cString\u003e"
                }
              }
            ]
          },
          {
            "name": "setFreeTraitStack",
            "returns": {
              "type": {
                "nullable": false,
                "basic": "void"
              }
            },
            "modifiers": [
              "public"
            ],
            "parameters": [
              {
                "notes": "the FreeTraitStack to set",
                "name": "FreeTraitStack",
                "type": {
                  "nullable": true,
                  "basic": "Stack",
                  "full": "Stack\u003cString\u003e"
                }
              }
            ]
          },
          {
            "name": "setIconPath",
            "returns": {
              "type": {
                "nullable": false,
                "basic": "void"
              }
            },
            "modifiers": [
              "public"
            ],
            "parameters": [
              {
                "notes": "the IconPath to set",
                "name": "IconPath",
                "type": {
                  "nullable": true,
                  "basic": "String"
                }
              }
            ]
          },
          {
            "name": "setName",
            "returns": {
              "type": {
                "nullable": false,
                "basic": "void"
              }
            },
            "modifiers": [
              "public"
            ],
            "parameters": [
              {
                "notes": "the name to set",
                "name": "name",
                "type": {
                  "nullable": true,
                  "basic": "String"
                }
              }
            ]
          },
          {
            "name": "setType",
            "returns": {
              "type": {
                "nullable": false,
                "basic": "void"
              }
            },
            "modifiers": [
              "public"
            ],
            "parameters": [
              {
                "notes": "the type to set",
                "name": "type",
                "type": {
                  "nullable": true,
                  "basic": "String"
                }
              }
            ]
          }
        ],
        "modifiers": [
          "public",
          "static"
        ],
        "fields": {
          "IconPath": {
            "deprecated": false,
            "name": "IconPath",
            "modifiers": [
              "public"
            ],
            "type": {
              "nullable": true,
              "basic": "String"
            }
          },
          "cost": {
            "deprecated": false,
            "name": "cost",
            "modifiers": [
              "public"
            ],
            "type": {
              "nullable": false,
              "basic": "int"
            }
          },
          "XPBoostMap": {
            "deprecated": false,
            "name": "XPBoostMap",
            "modifiers": [
              "public"
            ],
            "type": {
              "nullable": true,
              "basic": "HashMap"
            }
          },
          "texture": {
            "deprecated": false,
            "name": "texture",
            "modifiers": [
              "public"
            ],
            "type": {
              "nullable": true,
              "basic": "Texture"
            }
          },
          "name": {
            "deprecated": false,
            "name": "name",
            "modifiers": [
              "public"
            ],
            "type": {
              "nullable": true,
              "basic": "String"
            }
          },
          "description": {
            "deprecated": false,
            "name": "description",
            "modifiers": [
              "public"
            ],
            "type": {
              "nullable": true,
              "basic": "String"
            }
          },
          "type": {
            "deprecated": false,
            "name": "type",
            "modifiers": [
              "public"
            ],
            "type": {
              "nullable": true,
              "basic": "String"
            }
          },
          "FreeTraitStack": {
            "deprecated": false,
            "name": "FreeTraitStack",
            "modifiers": [
              "public"
            ],
            "type": {
              "nullable": true,
              "basic": "Stack"
            }
          }
        },
        "javaType": "class"
      }
    }
  }
}