{
  "$schema": "https://raw.githubusercontent.com/asledgehammer/PZ-Rosetta-Schema/main/rosetta-schema.json",
  "namespaces": {
    "zombie-radio-StorySounds": {
      "SLSoundManager": {
        "notes": "Turbo   Story line sound manager",
        "extends": "Object",
        "methods": [
          {
            "name": "getDebug",
            "returns": {
              "type": {
                "nullable": false,
                "basic": "boolean"
              }
            },
            "modifiers": [
              "public"
            ]
          },
          {
            "name": "getInstance",
            "returns": {
              "type": {
                "nullable": true,
                "basic": "SLSoundManager"
              }
            },
            "modifiers": [
              "public",
              "static"
            ]
          },
          {
            "name": "getLuaDebug",
            "returns": {
              "type": {
                "nullable": false,
                "basic": "boolean"
              }
            },
            "modifiers": [
              "public"
            ]
          },
          {
            "name": "getRandomBorderPosition",
            "returns": {
              "type": {
                "nullable": true,
                "basic": "Vector2"
              }
            },
            "modifiers": [
              "public"
            ]
          },
          {
            "name": "getRandomBorderRange",
            "returns": {
              "type": {
                "nullable": false,
                "basic": "float"
              }
            },
            "modifiers": [
              "public"
            ]
          },
          {
            "name": "getStorySounds",
            "returns": {
              "type": {
                "nullable": true,
                "basic": "ArrayList"
              }
            },
            "modifiers": [
              "public"
            ]
          },
          {
            "name": "init",
            "returns": {
              "type": {
                "nullable": false,
                "basic": "void"
              }
            },
            "modifiers": [
              "public"
            ]
          },
          {
            "name": "loadSounds",
            "returns": {
              "type": {
                "nullable": false,
                "basic": "void"
              }
            },
            "modifiers": [
              "public"
            ]
          },
          {
            "name": "print",
            "returns": {
              "type": {
                "nullable": false,
                "basic": "void"
              }
            },
            "modifiers": [
              "public"
            ],
            "parameters": [
              {
                "name": "line",
                "type": {
                  "nullable": true,
                  "basic": "String"
                }
              }
            ]
          },
          {
            "name": "render",
            "returns": {
              "type": {
                "nullable": false,
                "basic": "void"
              }
            },
            "modifiers": [
              "public"
            ]
          },
          {
            "name": "renderDebug",
            "returns": {
              "type": {
                "nullable": false,
                "basic": "void"
              }
            },
            "modifiers": [
              "public"
            ]
          },
          {
            "name": "thunderTest",
            "returns": {
              "type": {
                "nullable": false,
                "basic": "void"
              }
            },
            "modifiers": [
              "public"
            ]
          },
          {
            "name": "update",
            "returns": {
              "type": {
                "nullable": false,
                "basic": "void"
              }
            },
            "modifiers": [
              "public"
            ],
            "parameters": [
              {
                "name": "storylineDay",
                "type": {
                  "nullable": false,
                  "basic": "int"
                }
              },
              {
                "name": "hour",
                "type": {
                  "nullable": false,
                  "basic": "int"
                }
              },
              {
                "name": "min",
                "type": {
                  "nullable": false,
                  "basic": "int"
                }
              }
            ]
          },
          {
            "name": "updateKeys",
            "returns": {
              "type": {
                "nullable": false,
                "basic": "void"
              }
            },
            "modifiers": [
              "public"
            ]
          }
        ],
        "modifiers": [
          "public",
          "final"
        ],
        "fields": {
          "Emitter": {
            "deprecated": false,
            "name": "Emitter",
            "modifiers": [
              "public",
              "static"
            ],
            "type": {
              "nullable": true,
              "basic": "StoryEmitter"
            }
          },
          "LUA_DEBUG": {
            "deprecated": false,
            "name": "LUA_DEBUG",
            "modifiers": [
              "public",
              "static"
            ],
            "type": {
              "nullable": false,
              "basic": "boolean"
            }
          },
          "ENABLED": {
            "deprecated": false,
            "name": "ENABLED",
            "modifiers": [
              "public",
              "static"
            ],
            "type": {
              "nullable": false,
              "basic": "boolean"
            }
          },
          "DEBUG": {
            "deprecated": false,
            "name": "DEBUG",
            "modifiers": [
              "public",
              "static"
            ],
            "type": {
              "nullable": false,
              "basic": "boolean"
            }
          }
        },
        "javaType": "class"
      }
    }
  }
}