{
  "$schema": "https://raw.githubusercontent.com/asledgehammer/PZ-Rosetta-Schema/main/rosetta-schema.json",
  "namespaces": {
    "org-lwjglx-input": {
      "Keyboard": {
        "extends": "Object",
        "fields": {
          "KEY_A": {
            "deprecated": true,
            "name": "KEY_A",
            "modifiers": [
              "public",
              "static",
              "final"
            ],
            "type": {
              "nullable": true,
              "basic": "int",
              "full": "int"
            }
          },
          "KEY_C": {
            "deprecated": true,
            "name": "KEY_C",
            "modifiers": [
              "public",
              "static",
              "final"
            ],
            "type": {
              "nullable": true,
              "basic": "int",
              "full": "int"
            }
          },
          "KEY_B": {
            "deprecated": true,
            "name": "KEY_B",
            "modifiers": [
              "public",
              "static",
              "final"
            ],
            "type": {
              "nullable": true,
              "basic": "int",
              "full": "int"
            }
          },
          "KEY_DELETE": {
            "deprecated": true,
            "name": "KEY_DELETE",
            "modifiers": [
              "public",
              "static",
              "final"
            ],
            "type": {
              "nullable": true,
              "basic": "int",
              "full": "int"
            }
          },
          "KEY_E": {
            "deprecated": true,
            "name": "KEY_E",
            "modifiers": [
              "public",
              "static",
              "final"
            ],
            "type": {
              "nullable": true,
              "basic": "int",
              "full": "int"
            }
          },
          "KEY_D": {
            "deprecated": true,
            "name": "KEY_D",
            "modifiers": [
              "public",
              "static",
              "final"
            ],
            "type": {
              "nullable": true,
              "basic": "int",
              "full": "int"
            }
          },
          "KEY_G": {
            "deprecated": true,
            "name": "KEY_G",
            "modifiers": [
              "public",
              "static",
              "final"
            ],
            "type": {
              "nullable": true,
              "basic": "int",
              "full": "int"
            }
          },
          "KEY_F": {
            "deprecated": true,
            "name": "KEY_F",
            "modifiers": [
              "public",
              "static",
              "final"
            ],
            "type": {
              "nullable": true,
              "basic": "int",
              "full": "int"
            }
          },
          "KEY_I": {
            "deprecated": true,
            "name": "KEY_I",
            "modifiers": [
              "public",
              "static",
              "final"
            ],
            "type": {
              "nullable": true,
              "basic": "int",
              "full": "int"
            }
          },
          "KEY_H": {
            "deprecated": true,
            "name": "KEY_H",
            "modifiers": [
              "public",
              "static",
              "final"
            ],
            "type": {
              "nullable": true,
              "basic": "int",
              "full": "int"
            }
          },
          "KEY_K": {
            "deprecated": true,
            "name": "KEY_K",
            "modifiers": [
              "public",
              "static",
              "final"
            ],
            "type": {
              "nullable": true,
              "basic": "int",
              "full": "int"
            }
          },
          "KEY_INSERT": {
            "deprecated": true,
            "name": "KEY_INSERT",
            "modifiers": [
              "public",
              "static",
              "final"
            ],
            "type": {
              "nullable": true,
              "basic": "int",
              "full": "int"
            }
          },
          "KEY_J": {
            "deprecated": true,
            "name": "KEY_J",
            "modifiers": [
              "public",
              "static",
              "final"
            ],
            "type": {
              "nullable": true,
              "basic": "int",
              "full": "int"
            }
          },
          "KEY_COMMA": {
            "deprecated": true,
            "name": "KEY_COMMA",
            "modifiers": [
              "public",
              "static",
              "final"
            ],
            "type": {
              "nullable": true,
              "basic": "int",
              "full": "int"
            }
          },
          "KEY_M": {
            "deprecated": true,
            "name": "KEY_M",
            "modifiers": [
              "public",
              "static",
              "final"
            ],
            "type": {
              "nullable": true,
              "basic": "int",
              "full": "int"
            }
          },
          "KEY_L": {
            "deprecated": true,
            "name": "KEY_L",
            "modifiers": [
              "public",
              "static",
              "final"
            ],
            "type": {
              "nullable": true,
              "basic": "int",
              "full": "int"
            }
          },
          "KEY_O": {
            "deprecated": true,
            "name": "KEY_O",
            "modifiers": [
              "public",
              "static",
              "final"
            ],
            "type": {
              "nullable": true,
              "basic": "int",
              "full": "int"
            }
          },
          "KEY_N": {
            "deprecated": true,
            "name": "KEY_N",
            "modifiers": [
              "public",
              "static",
              "final"
            ],
            "type": {
              "nullable": true,
              "basic": "int",
              "full": "int"
            }
          },
          "KEY_Q": {
            "deprecated": true,
            "name": "KEY_Q",
            "modifiers": [
              "public",
              "static",
              "final"
            ],
            "type": {
              "nullable": true,
              "basic": "int",
              "full": "int"
            }
          },
          "KEY_P": {
            "deprecated": true,
            "name": "KEY_P",
            "modifiers": [
              "public",
              "static",
              "final"
            ],
            "type": {
              "nullable": true,
              "basic": "int",
              "full": "int"
            }
          },
          "KEY_S": {
            "deprecated": true,
            "name": "KEY_S",
            "modifiers": [
              "public",
              "static",
              "final"
            ],
            "type": {
              "nullable": true,
              "basic": "int",
              "full": "int"
            }
          },
          "KEY_R": {
            "deprecated": true,
            "name": "KEY_R",
            "modifiers": [
              "public",
              "static",
              "final"
            ],
            "type": {
              "nullable": true,
              "basic": "int",
              "full": "int"
            }
          },
          "KEY_MINUS": {
            "deprecated": true,
            "name": "KEY_MINUS",
            "modifiers": [
              "public",
              "static",
              "final"
            ],
            "type": {
              "nullable": true,
              "basic": "int",
              "full": "int"
            }
          },
          "KEY_U": {
            "deprecated": true,
            "name": "KEY_U",
            "modifiers": [
              "public",
              "static",
              "final"
            ],
            "type": {
              "nullable": true,
              "basic": "int",
              "full": "int"
            }
          },
          "KEY_T": {
            "deprecated": true,
            "name": "KEY_T",
            "modifiers": [
              "public",
              "static",
              "final"
            ],
            "type": {
              "nullable": true,
              "basic": "int",
              "full": "int"
            }
          },
          "KEY_GRAVE": {
            "deprecated": true,
            "name": "KEY_GRAVE",
            "modifiers": [
              "public",
              "static",
              "final"
            ],
            "type": {
              "nullable": true,
              "basic": "int",
              "full": "int"
            }
          },
          "KEY_W": {
            "deprecated": true,
            "name": "KEY_W",
            "modifiers": [
              "public",
              "static",
              "final"
            ],
            "type": {
              "nullable": true,
              "basic": "int",
              "full": "int"
            }
          },
          "KEY_V": {
            "deprecated": true,
            "name": "KEY_V",
            "modifiers": [
              "public",
              "static",
              "final"
            ],
            "type": {
              "nullable": true,
              "basic": "int",
              "full": "int"
            }
          },
          "KEY_Y": {
            "deprecated": true,
            "name": "KEY_Y",
            "modifiers": [
              "public",
              "static",
              "final"
            ],
            "type": {
              "nullable": true,
              "basic": "int",
              "full": "int"
            }
          },
          "KEY_X": {
            "deprecated": true,
            "name": "KEY_X",
            "modifiers": [
              "public",
              "static",
              "final"
            ],
            "type": {
              "nullable": true,
              "basic": "int",
              "full": "int"
            }
          },
          "KEY_CIRCUMFLEX": {
            "deprecated": true,
            "name": "KEY_CIRCUMFLEX",
            "modifiers": [
              "public",
              "static",
              "final"
            ],
            "type": {
              "nullable": true,
              "basic": "int",
              "full": "int"
            }
          },
          "KEY_Z": {
            "deprecated": true,
            "name": "KEY_Z",
            "modifiers": [
              "public",
              "static",
              "final"
            ],
            "type": {
              "nullable": true,
              "basic": "int",
              "full": "int"
            }
          },
          "KEY_BACKSLASH": {
            "deprecated": true,
            "name": "KEY_BACKSLASH",
            "modifiers": [
              "public",
              "static",
              "final"
            ],
            "type": {
              "nullable": true,
              "basic": "int",
              "full": "int"
            }
          },
          "KEY_SEMICOLON": {
            "deprecated": true,
            "name": "KEY_SEMICOLON",
            "modifiers": [
              "public",
              "static",
              "final"
            ],
            "type": {
              "nullable": true,
              "basic": "int",
              "full": "int"
            }
          },
          "KEY_MULTIPLY": {
            "deprecated": true,
            "name": "KEY_MULTIPLY",
            "modifiers": [
              "public",
              "static",
              "final"
            ],
            "type": {
              "nullable": true,
              "basic": "int",
              "full": "int"
            }
          },
          "KEY_RSHIFT": {
            "deprecated": true,
            "name": "KEY_RSHIFT",
            "modifiers": [
              "public",
              "static",
              "final"
            ],
            "type": {
              "nullable": true,
              "basic": "int",
              "full": "int"
            }
          },
          "KEY_NUMLOCK": {
            "deprecated": true,
            "name": "KEY_NUMLOCK",
            "modifiers": [
              "public",
              "static",
              "final"
            ],
            "type": {
              "nullable": true,
              "basic": "int",
              "full": "int"
            }
          },
          "KEY_SLEEP": {
            "deprecated": true,
            "name": "KEY_SLEEP",
            "modifiers": [
              "public",
              "static",
              "final"
            ],
            "type": {
              "nullable": true,
              "basic": "int",
              "full": "int"
            }
          },
          "KEY_NUMPAD7": {
            "deprecated": true,
            "name": "KEY_NUMPAD7",
            "modifiers": [
              "public",
              "static",
              "final"
            ],
            "type": {
              "nullable": true,
              "basic": "int",
              "full": "int"
            }
          },
          "KEY_NUMPAD8": {
            "deprecated": true,
            "name": "KEY_NUMPAD8",
            "modifiers": [
              "public",
              "static",
              "final"
            ],
            "type": {
              "nullable": true,
              "basic": "int",
              "full": "int"
            }
          },
          "KEY_TAB": {
            "deprecated": true,
            "name": "KEY_TAB",
            "modifiers": [
              "public",
              "static",
              "final"
            ],
            "type": {
              "nullable": true,
              "basic": "int",
              "full": "int"
            }
          },
          "KEY_NUMPAD5": {
            "deprecated": true,
            "name": "KEY_NUMPAD5",
            "modifiers": [
              "public",
              "static",
              "final"
            ],
            "type": {
              "nullable": true,
              "basic": "int",
              "full": "int"
            }
          },
          "KEY_NUMPAD6": {
            "deprecated": true,
            "name": "KEY_NUMPAD6",
            "modifiers": [
              "public",
              "static",
              "final"
            ],
            "type": {
              "nullable": true,
              "basic": "int",
              "full": "int"
            }
          },
          "KEY_SYSRQ": {
            "deprecated": true,
            "name": "KEY_SYSRQ",
            "modifiers": [
              "public",
              "static",
              "final"
            ],
            "type": {
              "nullable": true,
              "basic": "int",
              "full": "int"
            }
          },
          "KEY_NUMPAD9": {
            "deprecated": true,
            "name": "KEY_NUMPAD9",
            "modifiers": [
              "public",
              "static",
              "final"
            ],
            "type": {
              "nullable": true,
              "basic": "int",
              "full": "int"
            }
          },
          "KEY_NUMPAD0": {
            "deprecated": true,
            "name": "KEY_NUMPAD0",
            "modifiers": [
              "public",
              "static",
              "final"
            ],
            "type": {
              "nullable": true,
              "basic": "int",
              "full": "int"
            }
          },
          "KEY_APOSTROPHE": {
            "deprecated": true,
            "name": "KEY_APOSTROPHE",
            "modifiers": [
              "public",
              "static",
              "final"
            ],
            "type": {
              "nullable": true,
              "basic": "int",
              "full": "int"
            }
          },
          "KEY_CONVERT": {
            "deprecated": true,
            "name": "KEY_CONVERT",
            "modifiers": [
              "public",
              "static",
              "final"
            ],
            "type": {
              "nullable": true,
              "basic": "int",
              "full": "int"
            }
          },
          "KEY_NUMPAD3": {
            "deprecated": true,
            "name": "KEY_NUMPAD3",
            "modifiers": [
              "public",
              "static",
              "final"
            ],
            "type": {
              "nullable": true,
              "basic": "int",
              "full": "int"
            }
          },
          "KEY_NUMPAD4": {
            "deprecated": true,
            "name": "KEY_NUMPAD4",
            "modifiers": [
              "public",
              "static",
              "final"
            ],
            "type": {
              "nullable": true,
              "basic": "int",
              "full": "int"
            }
          },
          "KEY_RMENU": {
            "deprecated": true,
            "name": "KEY_RMENU",
            "modifiers": [
              "public",
              "static",
              "final"
            ],
            "type": {
              "nullable": true,
              "basic": "int",
              "full": "int"
            }
          },
          "KEY_NUMPAD1": {
            "deprecated": true,
            "name": "KEY_NUMPAD1",
            "modifiers": [
              "public",
              "static",
              "final"
            ],
            "type": {
              "nullable": true,
              "basic": "int",
              "full": "int"
            }
          },
          "KEY_NUMPAD2": {
            "deprecated": true,
            "name": "KEY_NUMPAD2",
            "modifiers": [
              "public",
              "static",
              "final"
            ],
            "type": {
              "nullable": true,
              "basic": "int",
              "full": "int"
            }
          },
          "KEY_F7": {
            "deprecated": true,
            "name": "KEY_F7",
            "modifiers": [
              "public",
              "static",
              "final"
            ],
            "type": {
              "nullable": true,
              "basic": "int",
              "full": "int"
            }
          },
          "KEY_F6": {
            "deprecated": true,
            "name": "KEY_F6",
            "modifiers": [
              "public",
              "static",
              "final"
            ],
            "type": {
              "nullable": true,
              "basic": "int",
              "full": "int"
            }
          },
          "KEY_F9": {
            "deprecated": true,
            "name": "KEY_F9",
            "modifiers": [
              "public",
              "static",
              "final"
            ],
            "type": {
              "nullable": true,
              "basic": "int",
              "full": "int"
            }
          },
          "KEY_F8": {
            "deprecated": true,
            "name": "KEY_F8",
            "modifiers": [
              "public",
              "static",
              "final"
            ],
            "type": {
              "nullable": true,
              "basic": "int",
              "full": "int"
            }
          },
          "KEY_LEFT": {
            "deprecated": true,
            "name": "KEY_LEFT",
            "modifiers": [
              "public",
              "static",
              "final"
            ],
            "type": {
              "nullable": true,
              "basic": "int",
              "full": "int"
            }
          },
          "KEY_STOP": {
            "deprecated": true,
            "name": "KEY_STOP",
            "modifiers": [
              "public",
              "static",
              "final"
            ],
            "type": {
              "nullable": true,
              "basic": "int",
              "full": "int"
            }
          },
          "KEY_UNDERLINE": {
            "deprecated": true,
            "name": "KEY_UNDERLINE",
            "modifiers": [
              "public",
              "static",
              "final"
            ],
            "type": {
              "nullable": true,
              "basic": "int",
              "full": "int"
            }
          },
          "KEY_FUNCTION": {
            "deprecated": true,
            "name": "KEY_FUNCTION",
            "modifiers": [
              "public",
              "static",
              "final"
            ],
            "type": {
              "nullable": true,
              "basic": "int",
              "full": "int"
            }
          },
          "KEY_APPS": {
            "deprecated": true,
            "name": "KEY_APPS",
            "modifiers": [
              "public",
              "static",
              "final"
            ],
            "type": {
              "nullable": true,
              "basic": "int",
              "full": "int"
            }
          },
          "KEY_RBRACKET": {
            "deprecated": true,
            "name": "KEY_RBRACKET",
            "modifiers": [
              "public",
              "static",
              "final"
            ],
            "type": {
              "nullable": true,
              "basic": "int",
              "full": "int"
            }
          },
          "KEY_NOCONVERT": {
            "deprecated": true,
            "name": "KEY_NOCONVERT",
            "modifiers": [
              "public",
              "static",
              "final"
            ],
            "type": {
              "nullable": true,
              "basic": "int",
              "full": "int"
            }
          },
          "KEY_F1": {
            "deprecated": true,
            "name": "KEY_F1",
            "modifiers": [
              "public",
              "static",
              "final"
            ],
            "type": {
              "nullable": true,
              "basic": "int",
              "full": "int"
            }
          },
          "KEY_F3": {
            "deprecated": true,
            "name": "KEY_F3",
            "modifiers": [
              "public",
              "static",
              "final"
            ],
            "type": {
              "nullable": true,
              "basic": "int",
              "full": "int"
            }
          },
          "KEY_F2": {
            "deprecated": true,
            "name": "KEY_F2",
            "modifiers": [
              "public",
              "static",
              "final"
            ],
            "type": {
              "nullable": true,
              "basic": "int",
              "full": "int"
            }
          },
          "KEY_F5": {
            "deprecated": true,
            "name": "KEY_F5",
            "modifiers": [
              "public",
              "static",
              "final"
            ],
            "type": {
              "nullable": true,
              "basic": "int",
              "full": "int"
            }
          },
          "KEY_F4": {
            "deprecated": true,
            "name": "KEY_F4",
            "modifiers": [
              "public",
              "static",
              "final"
            ],
            "type": {
              "nullable": true,
              "basic": "int",
              "full": "int"
            }
          },
          "KEY_SUBTRACT": {
            "deprecated": true,
            "name": "KEY_SUBTRACT",
            "modifiers": [
              "public",
              "static",
              "final"
            ],
            "type": {
              "nullable": true,
              "basic": "int",
              "full": "int"
            }
          },
          "KEY_LMETA": {
            "deprecated": true,
            "name": "KEY_LMETA",
            "modifiers": [
              "public",
              "static",
              "final"
            ],
            "type": {
              "nullable": true,
              "basic": "int",
              "full": "int"
            }
          },
          "KEY_NUMPADCOMMA": {
            "deprecated": true,
            "name": "KEY_NUMPADCOMMA",
            "modifiers": [
              "public",
              "static",
              "final"
            ],
            "type": {
              "nullable": true,
              "basic": "int",
              "full": "int"
            }
          },
          "KEY_UP": {
            "deprecated": true,
            "name": "KEY_UP",
            "modifiers": [
              "public",
              "static",
              "final"
            ],
            "type": {
              "nullable": true,
              "basic": "int",
              "full": "int"
            }
          },
          "KEY_RWIN": {
            "deprecated": true,
            "name": "KEY_RWIN",
            "modifiers": [
              "public",
              "static",
              "final"
            ],
            "type": {
              "nullable": true,
              "basic": "int",
              "full": "int"
            }
          },
          "KEY_1": {
            "deprecated": true,
            "name": "KEY_1",
            "modifiers": [
              "public",
              "static",
              "final"
            ],
            "type": {
              "nullable": true,
              "basic": "int",
              "full": "int"
            }
          },
          "KEY_0": {
            "deprecated": true,
            "name": "KEY_0",
            "modifiers": [
              "public",
              "static",
              "final"
            ],
            "type": {
              "nullable": true,
              "basic": "int",
              "full": "int"
            }
          },
          "KEY_3": {
            "deprecated": true,
            "name": "KEY_3",
            "modifiers": [
              "public",
              "static",
              "final"
            ],
            "type": {
              "nullable": true,
              "basic": "int",
              "full": "int"
            }
          },
          "KEYBOARD_SIZE": {
            "deprecated": true,
            "name": "KEYBOARD_SIZE",
            "modifiers": [
              "public",
              "static",
              "final"
            ],
            "type": {
              "nullable": true,
              "basic": "int",
              "full": "int"
            }
          },
          "KEY_2": {
            "deprecated": true,
            "name": "KEY_2",
            "modifiers": [
              "public",
              "static",
              "final"
            ],
            "type": {
              "nullable": true,
              "basic": "int",
              "full": "int"
            }
          },
          "KEY_5": {
            "deprecated": true,
            "name": "KEY_5",
            "modifiers": [
              "public",
              "static",
              "final"
            ],
            "type": {
              "nullable": true,
              "basic": "int",
              "full": "int"
            }
          },
          "KEY_4": {
            "deprecated": true,
            "name": "KEY_4",
            "modifiers": [
              "public",
              "static",
              "final"
            ],
            "type": {
              "nullable": true,
              "basic": "int",
              "full": "int"
            }
          },
          "KEY_7": {
            "deprecated": true,
            "name": "KEY_7",
            "modifiers": [
              "public",
              "static",
              "final"
            ],
            "type": {
              "nullable": true,
              "basic": "int",
              "full": "int"
            }
          },
          "KEY_NUMPADENTER": {
            "deprecated": true,
            "name": "KEY_NUMPADENTER",
            "modifiers": [
              "public",
              "static",
              "final"
            ],
            "type": {
              "nullable": true,
              "basic": "int",
              "full": "int"
            }
          },
          "KEY_RIGHT": {
            "deprecated": true,
            "name": "KEY_RIGHT",
            "modifiers": [
              "public",
              "static",
              "final"
            ],
            "type": {
              "nullable": true,
              "basic": "int",
              "full": "int"
            }
          },
          "KEY_6": {
            "deprecated": true,
            "name": "KEY_6",
            "modifiers": [
              "public",
              "static",
              "final"
            ],
            "type": {
              "nullable": true,
              "basic": "int",
              "full": "int"
            }
          },
          "KEY_9": {
            "deprecated": true,
            "name": "KEY_9",
            "modifiers": [
              "public",
              "static",
              "final"
            ],
            "type": {
              "nullable": true,
              "basic": "int",
              "full": "int"
            }
          },
          "KEY_8": {
            "deprecated": true,
            "name": "KEY_8",
            "modifiers": [
              "public",
              "static",
              "final"
            ],
            "type": {
              "nullable": true,
              "basic": "int",
              "full": "int"
            }
          },
          "KEY_NONE": {
            "deprecated": true,
            "name": "KEY_NONE",
            "modifiers": [
              "public",
              "static",
              "final"
            ],
            "type": {
              "nullable": true,
              "basic": "int",
              "full": "int"
            }
          },
          "KEY_SPACE": {
            "deprecated": true,
            "name": "KEY_SPACE",
            "modifiers": [
              "public",
              "static",
              "final"
            ],
            "type": {
              "nullable": true,
              "basic": "int",
              "full": "int"
            }
          },
          "CHAR_NONE": {
            "deprecated": true,
            "name": "CHAR_NONE",
            "modifiers": [
              "public",
              "static",
              "final"
            ],
            "type": {
              "nullable": true,
              "basic": "int",
              "full": "int"
            }
          },
          "KEY_LSHIFT": {
            "deprecated": true,
            "name": "KEY_LSHIFT",
            "modifiers": [
              "public",
              "static",
              "final"
            ],
            "type": {
              "nullable": true,
              "basic": "int",
              "full": "int"
            }
          },
          "KEY_COLON": {
            "deprecated": true,
            "name": "KEY_COLON",
            "modifiers": [
              "public",
              "static",
              "final"
            ],
            "type": {
              "nullable": true,
              "basic": "int",
              "full": "int"
            }
          },
          "KEY_YEN": {
            "deprecated": true,
            "name": "KEY_YEN",
            "modifiers": [
              "public",
              "static",
              "final"
            ],
            "type": {
              "nullable": true,
              "basic": "int",
              "full": "int"
            }
          },
          "KEY_LCONTROL": {
            "deprecated": true,
            "name": "KEY_LCONTROL",
            "modifiers": [
              "public",
              "static",
              "final"
            ],
            "type": {
              "nullable": true,
              "basic": "int",
              "full": "int"
            }
          },
          "KEY_CAPITAL": {
            "deprecated": true,
            "name": "KEY_CAPITAL",
            "modifiers": [
              "public",
              "static",
              "final"
            ],
            "type": {
              "nullable": true,
              "basic": "int",
              "full": "int"
            }
          },
          "KEY_POWER": {
            "deprecated": true,
            "name": "KEY_POWER",
            "modifiers": [
              "public",
              "static",
              "final"
            ],
            "type": {
              "nullable": true,
              "basic": "int",
              "full": "int"
            }
          },
          "KEY_CLEAR": {
            "deprecated": true,
            "name": "KEY_CLEAR",
            "modifiers": [
              "public",
              "static",
              "final"
            ],
            "type": {
              "nullable": true,
              "basic": "int",
              "full": "int"
            }
          },
          "KEY_DIVIDE": {
            "deprecated": true,
            "name": "KEY_DIVIDE",
            "modifiers": [
              "public",
              "static",
              "final"
            ],
            "type": {
              "nullable": true,
              "basic": "int",
              "full": "int"
            }
          },
          "KEY_LMENU": {
            "deprecated": true,
            "name": "KEY_LMENU",
            "modifiers": [
              "public",
              "static",
              "final"
            ],
            "type": {
              "nullable": true,
              "basic": "int",
              "full": "int"
            }
          },
          "KEY_HOME": {
            "deprecated": true,
            "name": "KEY_HOME",
            "modifiers": [
              "public",
              "static",
              "final"
            ],
            "type": {
              "nullable": true,
              "basic": "int",
              "full": "int"
            }
          },
          "KEY_ESCAPE": {
            "deprecated": true,
            "name": "KEY_ESCAPE",
            "modifiers": [
              "public",
              "static",
              "final"
            ],
            "type": {
              "nullable": true,
              "basic": "int",
              "full": "int"
            }
          },
          "KEY_NUMPADEQUALS": {
            "deprecated": true,
            "name": "KEY_NUMPADEQUALS",
            "modifiers": [
              "public",
              "static",
              "final"
            ],
            "type": {
              "nullable": true,
              "basic": "int",
              "full": "int"
            }
          },
          "KEY_F10": {
            "deprecated": true,
            "name": "KEY_F10",
            "modifiers": [
              "public",
              "static",
              "final"
            ],
            "type": {
              "nullable": true,
              "basic": "int",
              "full": "int"
            }
          },
          "KEY_F11": {
            "deprecated": true,
            "name": "KEY_F11",
            "modifiers": [
              "public",
              "static",
              "final"
            ],
            "type": {
              "nullable": true,
              "basic": "int",
              "full": "int"
            }
          },
          "KEY_F12": {
            "deprecated": true,
            "name": "KEY_F12",
            "modifiers": [
              "public",
              "static",
              "final"
            ],
            "type": {
              "nullable": true,
              "basic": "int",
              "full": "int"
            }
          },
          "KEY_SECTION": {
            "deprecated": true,
            "name": "KEY_SECTION",
            "modifiers": [
              "public",
              "static",
              "final"
            ],
            "type": {
              "nullable": true,
              "basic": "int",
              "full": "int"
            }
          },
          "KEY_F17": {
            "deprecated": true,
            "name": "KEY_F17",
            "modifiers": [
              "public",
              "static",
              "final"
            ],
            "type": {
              "nullable": true,
              "basic": "int",
              "full": "int"
            }
          },
          "KEY_F18": {
            "deprecated": true,
            "name": "KEY_F18",
            "modifiers": [
              "public",
              "static",
              "final"
            ],
            "type": {
              "nullable": true,
              "basic": "int",
              "full": "int"
            }
          },
          "KEY_F19": {
            "deprecated": true,
            "name": "KEY_F19",
            "modifiers": [
              "public",
              "static",
              "final"
            ],
            "type": {
              "nullable": true,
              "basic": "int",
              "full": "int"
            }
          },
          "KEY_F13": {
            "deprecated": true,
            "name": "KEY_F13",
            "modifiers": [
              "public",
              "static",
              "final"
            ],
            "type": {
              "nullable": true,
              "basic": "int",
              "full": "int"
            }
          },
          "KEY_F14": {
            "deprecated": true,
            "name": "KEY_F14",
            "modifiers": [
              "public",
              "static",
              "final"
            ],
            "type": {
              "nullable": true,
              "basic": "int",
              "full": "int"
            }
          },
          "KEY_F15": {
            "deprecated": true,
            "name": "KEY_F15",
            "modifiers": [
              "public",
              "static",
              "final"
            ],
            "type": {
              "nullable": true,
              "basic": "int",
              "full": "int"
            }
          },
          "KEY_F16": {
            "deprecated": true,
            "name": "KEY_F16",
            "modifiers": [
              "public",
              "static",
              "final"
            ],
            "type": {
              "nullable": true,
              "basic": "int",
              "full": "int"
            }
          },
          "KEY_LWIN": {
            "deprecated": true,
            "name": "KEY_LWIN",
            "modifiers": [
              "public",
              "static",
              "final"
            ],
            "type": {
              "nullable": true,
              "basic": "int",
              "full": "int"
            }
          },
          "KEY_EQUALS": {
            "deprecated": true,
            "name": "KEY_EQUALS",
            "modifiers": [
              "public",
              "static",
              "final"
            ],
            "type": {
              "nullable": true,
              "basic": "int",
              "full": "int"
            }
          },
          "KEY_NEXT": {
            "deprecated": true,
            "name": "KEY_NEXT",
            "modifiers": [
              "public",
              "static",
              "final"
            ],
            "type": {
              "nullable": true,
              "basic": "int",
              "full": "int"
            }
          },
          "KEY_PAUSE": {
            "deprecated": true,
            "name": "KEY_PAUSE",
            "modifiers": [
              "public",
              "static",
              "final"
            ],
            "type": {
              "nullable": true,
              "basic": "int",
              "full": "int"
            }
          },
          "KEY_RETURN": {
            "deprecated": true,
            "name": "KEY_RETURN",
            "modifiers": [
              "public",
              "static",
              "final"
            ],
            "type": {
              "nullable": true,
              "basic": "int",
              "full": "int"
            }
          },
          "KEY_AT": {
            "deprecated": true,
            "name": "KEY_AT",
            "modifiers": [
              "public",
              "static",
              "final"
            ],
            "type": {
              "nullable": true,
              "basic": "int",
              "full": "int"
            }
          },
          "KEY_SLASH": {
            "deprecated": true,
            "name": "KEY_SLASH",
            "modifiers": [
              "public",
              "static",
              "final"
            ],
            "type": {
              "nullable": true,
              "basic": "int",
              "full": "int"
            }
          },
          "KEY_ADD": {
            "deprecated": true,
            "name": "KEY_ADD",
            "modifiers": [
              "public",
              "static",
              "final"
            ],
            "type": {
              "nullable": true,
              "basic": "int",
              "full": "int"
            }
          },
          "KEY_AX": {
            "deprecated": true,
            "name": "KEY_AX",
            "modifiers": [
              "public",
              "static",
              "final"
            ],
            "type": {
              "nullable": true,
              "basic": "int",
              "full": "int"
            }
          },
          "KEY_KANA": {
            "deprecated": true,
            "name": "KEY_KANA",
            "modifiers": [
              "public",
              "static",
              "final"
            ],
            "type": {
              "nullable": true,
              "basic": "int",
              "full": "int"
            }
          },
          "KEY_LBRACKET": {
            "deprecated": true,
            "name": "KEY_LBRACKET",
            "modifiers": [
              "public",
              "static",
              "final"
            ],
            "type": {
              "nullable": true,
              "basic": "int",
              "full": "int"
            }
          },
          "KEY_KANJI": {
            "deprecated": true,
            "name": "KEY_KANJI",
            "modifiers": [
              "public",
              "static",
              "final"
            ],
            "type": {
              "nullable": true,
              "basic": "int",
              "full": "int"
            }
          },
          "KEY_BACK": {
            "deprecated": true,
            "name": "KEY_BACK",
            "modifiers": [
              "public",
              "static",
              "final"
            ],
            "type": {
              "nullable": true,
              "basic": "int",
              "full": "int"
            }
          },
          "KEY_PRIOR": {
            "deprecated": true,
            "name": "KEY_PRIOR",
            "modifiers": [
              "public",
              "static",
              "final"
            ],
            "type": {
              "nullable": true,
              "basic": "int",
              "full": "int"
            }
          },
          "KEY_UNLABELED": {
            "deprecated": true,
            "name": "KEY_UNLABELED",
            "modifiers": [
              "public",
              "static",
              "final"
            ],
            "type": {
              "nullable": true,
              "basic": "int",
              "full": "int"
            }
          },
          "KEY_RMETA": {
            "deprecated": true,
            "name": "KEY_RMETA",
            "modifiers": [
              "public",
              "static",
              "final"
            ],
            "type": {
              "nullable": true,
              "basic": "int",
              "full": "int"
            }
          },
          "KEY_DOWN": {
            "deprecated": true,
            "name": "KEY_DOWN",
            "modifiers": [
              "public",
              "static",
              "final"
            ],
            "type": {
              "nullable": true,
              "basic": "int",
              "full": "int"
            }
          },
          "KEY_PERIOD": {
            "deprecated": true,
            "name": "KEY_PERIOD",
            "modifiers": [
              "public",
              "static",
              "final"
            ],
            "type": {
              "nullable": true,
              "basic": "int",
              "full": "int"
            }
          },
          "KEY_SCROLL": {
            "deprecated": true,
            "name": "KEY_SCROLL",
            "modifiers": [
              "public",
              "static",
              "final"
            ],
            "type": {
              "nullable": true,
              "basic": "int",
              "full": "int"
            }
          },
          "KEY_RCONTROL": {
            "deprecated": true,
            "name": "KEY_RCONTROL",
            "modifiers": [
              "public",
              "static",
              "final"
            ],
            "type": {
              "nullable": true,
              "basic": "int",
              "full": "int"
            }
          },
          "KEY_DECIMAL": {
            "deprecated": true,
            "name": "KEY_DECIMAL",
            "modifiers": [
              "public",
              "static",
              "final"
            ],
            "type": {
              "nullable": true,
              "basic": "int",
              "full": "int"
            }
          },
          "KEY_END": {
            "deprecated": true,
            "name": "KEY_END",
            "modifiers": [
              "public",
              "static",
              "final"
            ],
            "type": {
              "nullable": true,
              "basic": "int",
              "full": "int"
            }
          }
        },
        "javaType": "class"
      }
    }
  }
}